BTCAddressGen/BTCAddressGen.py
BTCAddressGen/__init__.py
publicKey2btcAddress-0.0.2.dist-info/METADATA
publicKey2btcAddress-0.0.2.dist-info/WHEEL
publicKey2btcAddress-0.0.2.dist-info/top_level.txt
publicKey2btcAddress-0.0.2.dist-info/RECORD
