Metadata-Version: 2.1
Name: publicKey2btcAddress
Version: 0.0.2
Summary: simple tool
Home-page: https://github.com/Nevquit/btc_address
Author: vSir
Author-email: weiguo341@gmail.com
Classifier: Programming Language :: Python :: 3
Classifier: License :: OSI Approved :: MIT License
Classifier: Operating System :: OS Independent
Requires-Dist: bit (==0.7.2)
